hilo_mpc/__init__.py
hilo_mpc/library/__init__.py
hilo_mpc/library/models.py
hilo_mpc/modules/__init__.py
hilo_mpc/modules/base.py
hilo_mpc/modules/control_loop.py
hilo_mpc/modules/controller/__init__.py
hilo_mpc/modules/controller/base.py
hilo_mpc/modules/controller/lqr.py
hilo_mpc/modules/controller/mpc.py
hilo_mpc/modules/controller/ocp.py
hilo_mpc/modules/controller/pid.py
hilo_mpc/modules/dynamic_model/__init__.py
hilo_mpc/modules/dynamic_model/dynamic_model.py
hilo_mpc/modules/embedded/__init__.py
hilo_mpc/modules/embedded/muaompc.py
hilo_mpc/modules/estimator/__init__.py
hilo_mpc/modules/estimator/base.py
hilo_mpc/modules/estimator/kf.py
hilo_mpc/modules/estimator/mhe.py
hilo_mpc/modules/estimator/pf.py
hilo_mpc/modules/machine_learning/__init__.py
hilo_mpc/modules/machine_learning/base.py
hilo_mpc/modules/machine_learning/gp/__init__.py
hilo_mpc/modules/machine_learning/gp/gp.py
hilo_mpc/modules/machine_learning/gp/inference.py
hilo_mpc/modules/machine_learning/gp/kernel.py
hilo_mpc/modules/machine_learning/gp/likelihood.py
hilo_mpc/modules/machine_learning/gp/mean.py
hilo_mpc/modules/machine_learning/nn/__init__.py
hilo_mpc/modules/machine_learning/nn/layer.py
hilo_mpc/modules/machine_learning/nn/nn.py
hilo_mpc/modules/object.py
hilo_mpc/modules/optimizer.py
hilo_mpc/plugins/__init__.py
hilo_mpc/plugins/bokeh/__init__.py
hilo_mpc/plugins/bokeh/plot.py
hilo_mpc/plugins/io/__init__.py
hilo_mpc/plugins/io/opcua_async.py
hilo_mpc/plugins/io/opcua_connector.py
hilo_mpc/plugins/io/opcua_simple_control_loop.py
hilo_mpc/plugins/latex/__init__.py
hilo_mpc/plugins/latex/plot.py
hilo_mpc/plugins/matplotlib/__init__.py
hilo_mpc/plugins/matplotlib/plot.py
hilo_mpc/plugins/plugins.py
hilo_mpc/plugins/pytorch/__init__.py
hilo_mpc/plugins/pytorch/wrapper.py
hilo_mpc/plugins/sklearn/__init__.py
hilo_mpc/plugins/sklearn/wrapper.py
hilo_mpc/plugins/tensorboard/__init__.py
hilo_mpc/plugins/tensorboard/wrapper.py
hilo_mpc/plugins/tensorflow/__init__.py
hilo_mpc-2.1.0.dist-info/METADATA
hilo_mpc-2.1.0.dist-info/WHEEL
hilo_mpc-2.1.0.dist-info/licenses/LICENSE
hilo_mpc-2.1.0.dist-info/RECORD
