Metadata-Version: 2.4
Name: hilo-mpc
Version: 2.1.0
Summary: HILO-MPC is a toolbox for easy, flexible and fast development of machine-learning-supported optimal control and estimation problems
License: LGPL-3.0
License-File: LICENSE
Keywords: machine-learning,neural-networks,gaussian-processes,hybrid-modeling,model-based-optimization,model-predictive-control,mpc,trajectory-tracking-mpc,path-following-mpc,moving-horizon-estimation,mhe,lqr,pid,kalman-filters,particle-filters
Author: Johannes Pohlodek
Maintainer: HILO-MPC Developers
Requires-Python: >=3.10,<3.13
Classifier: Development Status :: 5 - Production/Stable
Classifier: Intended Audience :: Developers
Classifier: Intended Audience :: Education
Classifier: Intended Audience :: Science/Research
Classifier: License :: OSI Approved :: GNU Lesser General Public License v3 (LGPLv3)
Classifier: Operating System :: Microsoft :: Windows
Classifier: Operating System :: POSIX :: Linux
Classifier: Programming Language :: Python
Classifier: Programming Language :: Python :: 3
Classifier: Programming Language :: Python :: 3.10
Classifier: Programming Language :: Python :: 3.11
Classifier: Programming Language :: Python :: 3.12
Classifier: Programming Language :: Python :: 3 :: Only
Classifier: Topic :: Education
Classifier: Topic :: Scientific/Engineering
Classifier: Topic :: Software Development
Provides-Extra: connectivity
Provides-Extra: ml
Provides-Extra: pytorch
Provides-Extra: tensorflow
Provides-Extra: viz
Requires-Dist: asyncua (>=1.0.0) ; extra == "connectivity"
Requires-Dist: bokeh (>=2.3.0) ; extra == "viz"
Requires-Dist: casadi (>=3.6.5,<4.0.0)
Requires-Dist: keras (>=3.11.3) ; extra == "tensorflow"
Requires-Dist: matplotlib (>=3.0.0) ; extra == "viz"
Requires-Dist: numpy (<2.0)
Requires-Dist: pandas (>=2.0.0)
Requires-Dist: prettytable
Requires-Dist: scikit-learn (>=0.19.2) ; extra == "ml"
Requires-Dist: scipy
Requires-Dist: tensorboard (>=2.8.0) ; extra == "tensorflow"
Requires-Dist: tensorflow (>=2.8.0) ; extra == "tensorflow"
Requires-Dist: torch (>=1.2.0) ; extra == "pytorch"
Requires-Dist: torchvision (>=0.4.0) ; extra == "pytorch"
Project-URL: Bug Tracker, https://github.com/hilo-mpc/hilo-mpc/issues
Project-URL: Documentation, https://hilo-mpc.github.io/hilo-mpc/
Project-URL: Homepage, https://www.ccps.tu-darmstadt.de/research_ccps/hilo_mpc/
Project-URL: Repository, https://github.com/hilo-mpc/hilo-mpc
Project-URL: Source Code, https://github.com/hilo-mpc/hilo-mpc
